ckanext/__init__.py
ckanext/envvars/__init__.py
ckanext/envvars/plugin.py
ckanext/envvars/tests/__init__.py
ckanext/envvars/tests/test_base_envvars.py
ckanext_envvars-0.0.6.dist-info/LICENSE
ckanext_envvars-0.0.6.dist-info/METADATA
ckanext_envvars-0.0.6.dist-info/WHEEL
ckanext_envvars-0.0.6.dist-info/entry_points.txt
ckanext_envvars-0.0.6.dist-info/top_level.txt
ckanext_envvars-0.0.6.dist-info/RECORD
