Metadata-Version: 2.1
Name: ckanext-envvars
Version: 0.0.6
Summary: CKAN configuration settings available from env vars
Home-page: https://github.com/okfn/ckanext-envvars
Author: Brook Elgie
Author-email: brook.elgie@okfn.org
License: AGPL
Keywords: CKAN config
Classifier: Development Status :: 5 - Production/Stable
Classifier: License :: OSI Approved :: GNU Affero General Public License v3 or later (AGPLv3+)
Classifier: Programming Language :: Python :: 2.7
Classifier: Programming Language :: Python :: 3
License-File: LICENSE
Requires-Dist: ckantoolkit
